odoo/addons/l10n_br_pos_nfce/README.rst
odoo/addons/l10n_br_pos_nfce/__init__.py
odoo/addons/l10n_br_pos_nfce/__manifest__.py
odoo/addons/l10n_br_pos_nfce/demo/l10n_br_pos_nfce.xml
odoo/addons/l10n_br_pos_nfce/i18n/l10n_br_pos_nfce.pot
odoo/addons/l10n_br_pos_nfce/i18n/pt_BR.po
odoo/addons/l10n_br_pos_nfce/models/__init__.py
odoo/addons/l10n_br_pos_nfce/models/pos_config.py
odoo/addons/l10n_br_pos_nfce/models/pos_order.py
odoo/addons/l10n_br_pos_nfce/models/pos_payment_method.py
odoo/addons/l10n_br_pos_nfce/readme/CONFIGURE.rst
odoo/addons/l10n_br_pos_nfce/readme/CONTRIBUTORS.rst
odoo/addons/l10n_br_pos_nfce/readme/CREDITS.rst
odoo/addons/l10n_br_pos_nfce/readme/DESCRIPTION.rst
odoo/addons/l10n_br_pos_nfce/readme/HISTORY.rst
odoo/addons/l10n_br_pos_nfce/readme/INSTALL.rst
odoo/addons/l10n_br_pos_nfce/static/description/icon.png
odoo/addons/l10n_br_pos_nfce/static/description/index.html
odoo/addons/l10n_br_pos_nfce/static/src/css/ReceiptOrder.css
odoo/addons/l10n_br_pos_nfce/static/src/js/models.js
odoo/addons/l10n_br_pos_nfce/static/src/js/nfe-xml.js
odoo/addons/l10n_br_pos_nfce/static/src/js/utils.js
odoo/addons/l10n_br_pos_nfce/static/src/js/Screens/OrderManagementScreen/ControlButtons/CancelOrderButton.js
odoo/addons/l10n_br_pos_nfce/static/src/js/Screens/ReceiptScreen/NfceFiscalInfoReceipt.js
odoo/addons/l10n_br_pos_nfce/static/src/js/Screens/ReceiptScreen/NfceFooterReceipt.js
odoo/addons/l10n_br_pos_nfce/static/src/js/Screens/ReceiptScreen/NfceHeaderReceipt.js
odoo/addons/l10n_br_pos_nfce/static/src/js/Screens/ReceiptScreen/NfceItemReceipt.js
odoo/addons/l10n_br_pos_nfce/static/src/js/Screens/ReceiptScreen/NfceOrderReceipt.js
odoo/addons/l10n_br_pos_nfce/static/src/js/Screens/ReceiptScreen/NfcePaymentlineReceipt.js
odoo/addons/l10n_br_pos_nfce/static/src/js/Screens/ReceiptScreen/NfceTotalsReceipt.js
odoo/addons/l10n_br_pos_nfce/static/src/js/Screens/ReceiptScreen/ReceiptScreen.js
odoo/addons/l10n_br_pos_nfce/static/src/lib/xmlbuilder2.min.js
odoo14_addon_l10n_br_pos_nfce-14.0.1.3.2.dist-info/METADATA
odoo14_addon_l10n_br_pos_nfce-14.0.1.3.2.dist-info/WHEEL
odoo14_addon_l10n_br_pos_nfce-14.0.1.3.2.dist-info/top_level.txt
odoo14_addon_l10n_br_pos_nfce-14.0.1.3.2.dist-info/RECORD
